{
  "spider": "https://sp.118318.xyz/https://github.com/ivortang2024/TvboxSpider1.0/raw/refs/heads/master/jar/custom_spider.jar;md5;d1a67eb14f8887e3d15cf0ab4f2d6349",
  "sites": [
    {
      "key": "MissAV",
      "name": "MissAV",
      "type": 3,
      "api": "csp_Miss",
      "searchable": 1,
      "quickSearch": 1,
      "filterable": 1,
      "ext": "https://missav.com/cn/"
    },
    {
      "key": "MissAV-API",
      "name": "MissAV-API",
      "type": 1,
      "api": "https://miss-api.118318.xyz/api",
      "searchable": 1,
      "quickSearch": 1,
      "filterable": 1,
      "changeable": 2,
      "style": {
        "type": "rect",
        "ratio": 1.49
      }
    },
    {
      "key": "MissAV-API-CF",
      "name": "MissAV-API-CF",
      "type": 1,
      "api": "https://miss-api-cf.118318.xyz/api",
      "searchable": 1,
      "quickSearch": 1,
      "filterable": 1,
      "changeable": 2,
      "style": {
        "type": "rect",
        "ratio": 1.49
      }
    }
  ],
  "rules": [
    {
      "name": "proxy",
      "hosts": [
        "missav.com",
        "surrit.com"
      ]
    }
  ]
}